exceptions/__init__.py
exceptions/commander_exception.py
exceptions/executor_exception.py
pyexecutor/__init__.py
pyexecutor/commander.py
pyexecutor/executor.py
pyexecutor/exceptions/__init__.py
pyexecutor/exceptions/commander_exception.py
pyexecutor/exceptions/executor_exception.py
pyexecutor-0.0.4.dist-info/LICENSE.md
pyexecutor-0.0.4.dist-info/METADATA
pyexecutor-0.0.4.dist-info/WHEEL
pyexecutor-0.0.4.dist-info/top_level.txt
pyexecutor-0.0.4.dist-info/RECORD
